{"type":"FeatureCollection","features":[{"type":"Feature","geometry":{"type":"Polygon","coordinates":[[[2.8640579,50.5743272],[2.8643304,50.572539],[2.8671424,50.5727139],[2.86687,50.5745021],[2.8640579,50.5743272]]]},"properties":{"id":"CRS3035RES200mN3075800E3816400","idInspire":"CRS3035RES200m<br />N3075800E3816400","commune":"WICRES","people":"28","surfaceTotalPark":"","popParkIncluded":"n/a","popParkExcluded":"n/a","popSquareShare":"","squareMtePerCapita":"","surfaceTotalParkOms":"","popParkIncludedOms":"","popParkExcludedOms":"","popSquareShareOms":"","squareMtePerCapitaOms":"","commentParks":"","fillColor":"#060512","areaPerPeople":"","area":""}},{"type":"Feature","geometry":{"type":"Polygon","coordinates":[[[2.87449,50.5803911],[2.8747621,50.5786029],[2.8775745,50.5787776],[2.8773024,50.5805658],[2.87449,50.5803911]]]},"properties":{"id":"CRS3035RES200mN3076400E3817200","idInspire":"CRS3035RES200m<br />N3076400E3817200","commune":"FOURNES EN WEPPES","people":"2","surfaceTotalPark":"","popParkIncluded":"n/a","popParkExcluded":"n/a","popSquareShare":"","squareMtePerCapita":"","surfaceTotalParkOms":"","popParkIncludedOms":"","popParkExcludedOms":"","popSquareShareOms":"","squareMtePerCapitaOms":"","commentParks":"","fillColor":"#060512","areaPerPeople":"","area":""}},{"type":"Feature","geometry":{"type":"Polygon","coordinates":[[[2.8728566,50.5911202],[2.8731289,50.589332],[2.8759419,50.5895068],[2.8756697,50.591295],[2.8728566,50.5911202]]]},"properties":{"id":"CRS3035RES200mN3077600E3817200","idInspire":"CRS3035RES200m<br />N3077600E3817200","commune":"FOURNES EN WEPPES","people":"3","surfaceTotalPark":"","popParkIncluded":"n/a","popParkExcluded":"n/a","popSquareShare":"","squareMtePerCapita":"","surfaceTotalParkOms":"","popParkIncludedOms":"","popParkExcludedOms":"","popSquareShareOms":"","squareMtePerCapitaOms":"","commentParks":"","fillColor":"#060512","areaPerPeople":"","area":""}},{"type":"Feature","geometry":{"type":"Polygon","coordinates":[[[2.8725843,50.5929084],[2.8728566,50.5911202],[2.8756697,50.591295],[2.8753975,50.5930831],[2.8725843,50.5929084]]]},"properties":{"id":"CRS3035RES200mN3077800E3817200","idInspire":"CRS3035RES200m<br />N3077800E3817200","commune":"FOURNES EN WEPPES","people":"6","surfaceTotalPark":"","popParkIncluded":"n/a","popParkExcluded":"n/a","popSquareShare":"","squareMtePerCapita":"","surfaceTotalParkOms":"","popParkIncludedOms":"","popParkExcludedOms":"","popSquareShareOms":"","squareMtePerCapitaOms":"","commentParks":"","fillColor":"#060512","areaPerPeople":"","area":""}},{"type":"Feature","geometry":{"type":"Polygon","coordinates":[[[2.8598825,50.583093],[2.8601552,50.5813048],[2.8629677,50.5814798],[2.8626951,50.583268],[2.8598825,50.583093]]]},"properties":{"id":"CRS3035RES200mN3076800E3816200","idInspire":"CRS3035RES200m<br />N3076800E3816200","commune":"HERLIES","people":"69","surfaceTotalPark":"","popParkIncluded":"n/a","popParkExcluded":"n/a","popSquareShare":"","squareMtePerCapita":"","surfaceTotalParkOms":"","popParkIncludedOms":"","popParkExcludedOms":"","popSquareShareOms":"","squareMtePerCapitaOms":"","commentParks":"","fillColor":"#060512","areaPerPeople":"","area":""}},{"type":"Feature","geometry":{"type":"Polygon","coordinates":[[[2.859337,50.5866693],[2.8596098,50.5848811],[2.8624225,50.5850562],[2.8621498,50.5868443],[2.859337,50.5866693]]]},"properties":{"id":"CRS3035RES200mN3077200E3816200","idInspire":"CRS3035RES200m<br />N3077200E3816200","commune":"HERLIES","people":"5","surfaceTotalPark":"","popParkIncluded":"n/a","popParkExcluded":"n/a","popSquareShare":"","squareMtePerCapita":"","surfaceTotalParkOms":"","popParkIncludedOms":"","popParkExcludedOms":"","popSquareShareOms":"","squareMtePerCapitaOms":"","commentParks":"","fillColor":"#060512","areaPerPeople":"","area":""}},{"type":"Feature","geometry":{"type":"Polygon","coordinates":[[[2.8399215,50.5836539],[2.840195,50.5818658],[2.8430074,50.5820413],[2.8427341,50.5838294],[2.8399215,50.5836539]]]},"properties":{"id":"CRS3035RES200mN3077000E3814800","idInspire":"CRS3035RES200m<br />N3077000E3814800","commune":"HERLIES","people":"22","surfaceTotalPark":"","popParkIncluded":"n/a","popParkExcluded":"n/a","popSquareShare":"","squareMtePerCapita":"","surfaceTotalParkOms":"","popParkIncludedOms":"","popParkExcludedOms":"","popSquareShareOms":"","squareMtePerCapitaOms":"","commentParks":"","fillColor":"#060512","areaPerPeople":"","area":""}},{"type":"Feature","geometry":{"type":"Polygon","coordinates":[[[2.8562513,50.5882823],[2.8565242,50.5864942],[2.859337,50.5866693],[2.8590642,50.5884574],[2.8562513,50.5882823]]]},"properties":{"id":"CRS3035RES200mN3077400E3816000","idInspire":"CRS3035RES200m<br />N3077400E3816000","commune":"HERLIES","people":"20","surfaceTotalPark":"","popParkIncluded":"n/a","popParkExcluded":"n/a","popSquareShare":"","squareMtePerCapita":"","surfaceTotalParkOms":"","popParkIncludedOms":"","popParkExcludedOms":"","popSquareShareOms":"","squareMtePerCapitaOms":"","commentParks":"","fillColor":"#060512","areaPerPeople":"","area":""}},{"type":"Feature","geometry":{"type":"Polygon","coordinates":[[[2.8499978,50.5734515],[2.8502708,50.5716634],[2.8530827,50.5718386],[2.8528098,50.5736268],[2.8499978,50.5734515]]]},"properties":{"id":"CRS3035RES200mN3075800E3815400","idInspire":"CRS3035RES200m<br />N3075800E3815400","commune":"HERLIES","people":"6","surfaceTotalPark":"","popParkIncluded":"n/a","popParkExcluded":"n/a","popSquareShare":"","squareMtePerCapita":"","surfaceTotalParkOms":"","popParkIncludedOms":"","popParkExcludedOms":"","popSquareShareOms":"","squareMtePerCapitaOms":"","commentParks":"","fillColor":"#060512","areaPerPeople":"","area":""}},{"type":"Feature","geometry":{"type":"Polygon","coordinates":[[[2.8519909,50.5789912],[2.8522639,50.577203],[2.8550761,50.5773783],[2.8548033,50.5791664],[2.8519909,50.5789912]]]},"properties":{"id":"CRS3035RES200mN3076400E3815600","idInspire":"CRS3035RES200m<br />N3076400E3815600","commune":"HERLIES","people":"34","surfaceTotalPark":"","popParkIncluded":"n/a","popParkExcluded":"n/a","popSquareShare":"","squareMtePerCapita":"","surfaceTotalParkOms":"","popParkIncludedOms":"","popParkExcludedOms":"","popSquareShareOms":"","squareMtePerCapitaOms":"","commentParks":"","fillColor":"#060512","areaPerPeople":"","area":""}},{"type":"Feature","geometry":{"type":"Polygon","coordinates":[[[2.8458199,50.5822167],[2.8460932,50.5804286],[2.8489055,50.580604],[2.8486324,50.5823921],[2.8458199,50.5822167]]]},"properties":{"id":"CRS3035RES200mN3076800E3815200","idInspire":"CRS3035RES200m<br />N3076800E3815200","commune":"HERLIES","people":"34","surfaceTotalPark":"","popParkIncluded":"n/a","popParkExcluded":"n/a","popSquareShare":"","squareMtePerCapita":"","surfaceTotalParkOms":"","popParkIncludedOms":"","popParkExcludedOms":"","popSquareShareOms":"","squareMtePerCapitaOms":"","commentParks":"","fillColor":"#060512","areaPerPeople":"","area":""}},{"type":"Feature","geometry":{"type":"Polygon","coordinates":[[[2.8559784,50.5900704],[2.8562513,50.5882823],[2.8590642,50.5884574],[2.8587914,50.5902456],[2.8559784,50.5900704]]]},"properties":{"id":"CRS3035RES200mN3077600E3816000","idInspire":"CRS3035RES200m<br />N3077600E3816000","commune":"HERLIES","people":"18","surfaceTotalPark":"","popParkIncluded":"n/a","popParkExcluded":"n/a","popSquareShare":"","squareMtePerCapita":"","surfaceTotalParkOms":"","popParkIncludedOms":"","popParkExcludedOms":"","popSquareShareOms":"","squareMtePerCapitaOms":"","commentParks":"","fillColor":"#060512","areaPerPeople":"","area":""}},{"type":"Feature","geometry":{"type":"Polygon","coordinates":[[[2.8573428,50.5811297],[2.8576156,50.5793416],[2.8604279,50.5795167],[2.8601552,50.5813048],[2.8573428,50.5811297]]]},"properties":{"id":"CRS3035RES200mN3076600E3816000","idInspire":"CRS3035RES200m<br />N3076600E3816000","commune":"HERLIES","people":"184","surfaceTotalPark":"","popParkIncluded":"n/a","popParkExcluded":"n/a","popSquareShare":"","squareMtePerCapita":"","surfaceTotalParkOms":"","popParkIncludedOms":"","popParkExcludedOms":"","popSquareShareOms":"","squareMtePerCapitaOms":"","commentParks":"","fillColor":"#060512","areaPerPeople":"","area":""}},{"type":"Feature","geometry":{"type":"Polygon","coordinates":[[[2.8483592,50.5841803],[2.8486324,50.5823921],[2.8514449,50.5825674],[2.8511718,50.5843556],[2.8483592,50.5841803]]]},"properties":{"id":"CRS3035RES200mN3077000E3815400","idInspire":"CRS3035RES200m<br />N3077000E3815400","commune":"HERLIES","people":"2","surfaceTotalPark":"","popParkIncluded":"n/a","popParkExcluded":"n/a","popSquareShare":"","squareMtePerCapita":"","surfaceTotalParkOms":"","popParkIncludedOms":"","popParkExcludedOms":"","popSquareShareOms":"","squareMtePerCapitaOms":"","commentParks":"","fillColor":"#060512","areaPerPeople":"","area":""}},{"type":"Feature","geometry":{"type":"Polygon","coordinates":[[[2.8508168,50.5680871],[2.8510897,50.566299],[2.8539013,50.5664742],[2.8536284,50.5682623],[2.8508168,50.5680871]]]},"properties":{"id":"CRS3035RES200mN3075200E3815400","idInspire":"CRS3035RES200m<br />N3075200E3815400","commune":"HERLIES","people":"3","surfaceTotalPark":"","popParkIncluded":"n/a","popParkExcluded":"n/a","popSquareShare":"","squareMtePerCapita":"","surfaceTotalParkOms":"","popParkIncludedOms":"","popParkExcludedOms":"","popSquareShareOms":"","squareMtePerCapitaOms":"","commentParks":"","fillColor":"#060512","areaPerPeople":"","area":""}},{"type":"Feature","geometry":{"type":"Polygon","coordinates":[[[2.8463664,50.5786405],[2.8466396,50.5768524],[2.8494517,50.5770278],[2.8491786,50.5788159],[2.8463664,50.5786405]]]},"properties":{"id":"CRS3035RES200mN3076400E3815200","idInspire":"CRS3035RES200m<br />N3076400E3815200","commune":"HERLIES","people":"30","surfaceTotalPark":"","popParkIncluded":"n/a","popParkExcluded":"n/a","popSquareShare":"","squareMtePerCapita":"","surfaceTotalParkOms":"","popParkIncludedOms":"","popParkExcludedOms":"","popSquareShareOms":"","squareMtePerCapitaOms":"","commentParks":"","fillColor":"#060512","areaPerPeople":"","area":""}},{"type":"Feature","geometry":{"type":"Polygon","coordinates":[[[2.8466396,50.5768524],[2.8469127,50.5750643],[2.8497248,50.5752396],[2.8494517,50.5770278],[2.8466396,50.5768524]]]},"properties":{"id":"CRS3035RES200mN3076200E3815200","idInspire":"CRS3035RES200m<br />N3076200E3815200","commune":"HERLIES","people":"5","surfaceTotalPark":"","popParkIncluded":"n/a","popParkExcluded":"n/a","popSquareShare":"","squareMtePerCapita":"","surfaceTotalParkOms":"","popParkIncludedOms":"","popParkExcludedOms":"","popSquareShareOms":"","squareMtePerCapitaOms":"","commentParks":"","fillColor":"#060512","areaPerPeople":"","area":""}},{"type":"Feature","geometry":{"type":"Polygon","coordinates":[[[2.8514449,50.5825674],[2.8517179,50.5807793],[2.8545303,50.5809545],[2.8542574,50.5827427],[2.8514449,50.5825674]]]},"properties":{"id":"CRS3035RES200mN3076800E3815600","idInspire":"CRS3035RES200m<br />N3076800E3815600","commune":"HERLIES","people":"66","surfaceTotalPark":"","popParkIncluded":"n/a","popParkExcluded":"n/a","popSquareShare":"","squareMtePerCapita":"","surfaceTotalParkOms":"","popParkIncludedOms":"","popParkExcludedOms":"","popSquareShareOms":"","squareMtePerCapitaOms":"","commentParks":"","fillColor":"#060512","areaPerPeople":"","area":""}},{"type":"Feature","geometry":{"type":"Polygon","coordinates":[[[2.8545303,50.5809545],[2.8548033,50.5791664],[2.8576156,50.5793416],[2.8573428,50.5811297],[2.8545303,50.5809545]]]},"properties":{"id":"CRS3035RES200mN3076600E3815800","idInspire":"CRS3035RES200m<br />N3076600E3815800","commune":"HERLIES","people":"102","surfaceTotalPark":"","popParkIncluded":"n/a","popParkExcluded":"n/a","popSquareShare":"","squareMtePerCapita":"","surfaceTotalParkOms":"","popParkIncludedOms":"","popParkExcludedOms":"","popSquareShareOms":"","squareMtePerCapitaOms":"","commentParks":"","fillColor":"#060512","areaPerPeople":"","area":""}},{"type":"Feature","geometry":{"type":"Polygon","coordinates":[[[2.8565242,50.5864942],[2.8567971,50.584706],[2.8596098,50.5848811],[2.859337,50.5866693],[2.8565242,50.5864942]]]},"properties":{"id":"CRS3035RES200mN3077200E3816000","idInspire":"CRS3035RES200m<br />N3077200E3816000","commune":"HERLIES","people":"10","surfaceTotalPark":"","popParkIncluded":"n/a","popParkExcluded":"n/a","popSquareShare":"","squareMtePerCapita":"","surfaceTotalParkOms":"","popParkIncludedOms":"","popParkExcludedOms":"","popSquareShareOms":"","squareMtePerCapitaOms":"","commentParks":"","fillColor":"#060512","areaPerPeople":"","area":""}},{"type":"Feature","geometry":{"type":"Polygon","coordinates":[[[2.8522639,50.577203],[2.8525369,50.5754149],[2.855349,50.5755901],[2.8550761,50.5773783],[2.8522639,50.577203]]]},"properties":{"id":"CRS3035RES200mN3076200E3815600","idInspire":"CRS3035RES200m<br />N3076200E3815600","commune":"HERLIES","people":"90","surfaceTotalPark":"","popParkIncluded":"n/a","popParkExcluded":"n/a","popSquareShare":"","squareMtePerCapita":"","surfaceTotalParkOms":"","popParkIncludedOms":"","popParkExcludedOms":"","popSquareShareOms":"","squareMtePerCapitaOms":"","commentParks":"","fillColor":"#060512","areaPerPeople":"","area":""}},{"type":"Feature","geometry":{"type":"Polygon","coordinates":[[[2.8539845,50.5845308],[2.8542574,50.5827427],[2.85707,50.5829179],[2.8567971,50.584706],[2.8539845,50.5845308]]]},"properties":{"id":"CRS3035RES200mN3077000E3815800","idInspire":"CRS3035RES200m<br />N3077000E3815800","commune":"HERLIES","people":"12","surfaceTotalPark":"","popParkIncluded":"n/a","popParkExcluded":"n/a","popSquareShare":"","squareMtePerCapita":"","surfaceTotalParkOms":"","popParkIncludedOms":"","popParkExcludedOms":"","popSquareShareOms":"","squareMtePerCapitaOms":"","commentParks":"","fillColor":"#060512","areaPerPeople":"","area":""}},{"type":"Feature","geometry":{"type":"Polygon","coordinates":[[[2.8629677,50.5814798],[2.8632403,50.5796917],[2.8660527,50.5798666],[2.8657802,50.5816548],[2.8629677,50.5814798]]]},"properties":{"id":"CRS3035RES200mN3076600E3816400","idInspire":"CRS3035RES200m<br />N3076600E3816400","commune":"HERLIES","people":"28","surfaceTotalPark":"","popParkIncluded":"n/a","popParkExcluded":"n/a","popSquareShare":"","squareMtePerCapita":"","surfaceTotalParkOms":"","popParkIncludedOms":"","popParkExcludedOms":"","popSquareShareOms":"","squareMtePerCapitaOms":"","commentParks":"","fillColor":"#060512","areaPerPeople":"","area":""}},{"type":"Feature","geometry":{"type":"Polygon","coordinates":[[[2.8601552,50.5813048],[2.8604279,50.5795167],[2.8632403,50.5796917],[2.8629677,50.5814798],[2.8601552,50.5813048]]]},"properties":{"id":"CRS3035RES200mN3076600E3816200","idInspire":"CRS3035RES200m<br />N3076600E3816200","commune":"HERLIES","people":"120","surfaceTotalPark":"","popParkIncluded":"n/a","popParkExcluded":"n/a","popSquareShare":"","squareMtePerCapita":"","surfaceTotalParkOms":"","popParkIncludedOms":"","popParkExcludedOms":"","popSquareShareOms":"","squareMtePerCapitaOms":"","commentParks":"","fillColor":"#060512","areaPerPeople":"","area":""}},{"type":"Feature","geometry":{"type":"Polygon","coordinates":[[[2.8557055,50.5918586],[2.8559784,50.5900704],[2.8587914,50.5902456],[2.8585186,50.5920337],[2.8557055,50.5918586]]]},"properties":{"id":"CRS3035RES200mN3077800E3816000","idInspire":"CRS3035RES200m<br />N3077800E3816000","commune":"HERLIES","people":"18","surfaceTotalPark":"","popParkIncluded":"n/a","popParkExcluded":"n/a","popSquareShare":"","squareMtePerCapita":"","surfaceTotalParkOms":"","popParkIncludedOms":"","popParkExcludedOms":"","popSquareShareOms":"","squareMtePerCapitaOms":"","commentParks":"","fillColor":"#060512","areaPerPeople":"","area":""}},{"type":"Feature","geometry":{"type":"Polygon","coordinates":[[[2.8590642,50.5884574],[2.859337,50.5866693],[2.8621498,50.5868443],[2.8618771,50.5886325],[2.8590642,50.5884574]]]},"properties":{"id":"CRS3035RES200mN3077400E3816200","idInspire":"CRS3035RES200m<br />N3077400E3816200","commune":"HERLIES","people":"14","surfaceTotalPark":"","popParkIncluded":"n/a","popParkExcluded":"n/a","popSquareShare":"","squareMtePerCapita":"","surfaceTotalParkOms":"","popParkIncludedOms":"","popParkExcludedOms":"","popSquareShareOms":"","squareMtePerCapitaOms":"","commentParks":"","fillColor":"#060512","areaPerPeople":"","area":""}},{"type":"Feature","geometry":{"type":"Polygon","coordinates":[[[2.8446472,50.5713126],[2.8449204,50.5695245],[2.8477321,50.5696999],[2.847459,50.571488],[2.8446472,50.5713126]]]},"properties":{"id":"CRS3035RES200mN3075600E3815000","idInspire":"CRS3035RES200m<br />N3075600E3815000","commune":"HERLIES","people":"3","surfaceTotalPark":"","popParkIncluded":"n/a","popParkExcluded":"n/a","popSquareShare":"","squareMtePerCapita":"","surfaceTotalParkOms":"","popParkIncludedOms":"","popParkExcludedOms":"","popSquareShareOms":"","squareMtePerCapitaOms":"","commentParks":"","fillColor":"#060512","areaPerPeople":"","area":""}},{"type":"Feature","geometry":{"type":"Polygon","coordinates":[[[2.8508988,50.5861437],[2.8511718,50.5843556],[2.8539845,50.5845308],[2.8537115,50.586319],[2.8508988,50.5861437]]]},"properties":{"id":"CRS3035RES200mN3077200E3815600","idInspire":"CRS3035RES200m<br />N3077200E3815600","commune":"HERLIES","people":"3","surfaceTotalPark":"","popParkIncluded":"n/a","popParkExcluded":"n/a","popSquareShare":"","squareMtePerCapita":"","surfaceTotalParkOms":"","popParkIncludedOms":"","popParkExcludedOms":"","popSquareShareOms":"","squareMtePerCapitaOms":"","commentParks":"","fillColor":"#060512","areaPerPeople":"","area":""}},{"type":"Feature","geometry":{"type":"Polygon","coordinates":[[[2.8587914,50.5902456],[2.8590642,50.5884574],[2.8618771,50.5886325],[2.8616044,50.5904206],[2.8587914,50.5902456]]]},"properties":{"id":"CRS3035RES200mN3077600E3816200","idInspire":"CRS3035RES200m<br />N3077600E3816200","commune":"HERLIES","people":"4","surfaceTotalPark":"","popParkIncluded":"n/a","popParkExcluded":"n/a","popSquareShare":"","squareMtePerCapita":"","surfaceTotalParkOms":"","popParkIncludedOms":"","popParkExcludedOms":"","popSquareShareOms":"","squareMtePerCapitaOms":"","commentParks":"","fillColor":"#060512","areaPerPeople":"","area":""}},{"type":"Feature","geometry":{"type":"Polygon","coordinates":[[[2.8528098,50.5736268],[2.8530827,50.5718386],[2.8558946,50.5720138],[2.8556218,50.573802],[2.8528098,50.5736268]]]},"properties":{"id":"CRS3035RES200mN3075800E3815600","idInspire":"CRS3035RES200m<br />N3075800E3815600","commune":"HERLIES","people":"17","surfaceTotalPark":"","popParkIncluded":"n/a","popParkExcluded":"n/a","popSquareShare":"","squareMtePerCapita":"","surfaceTotalParkOms":"","popParkIncludedOms":"","popParkExcludedOms":"","popSquareShareOms":"","squareMtePerCapitaOms":"","commentParks":"","fillColor":"#060512","areaPerPeople":"","area":""}},{"type":"Feature","geometry":{"type":"Polygon","coordinates":[[[2.8427341,50.5838294],[2.8430074,50.5820413],[2.8458199,50.5822167],[2.8455466,50.5840049],[2.8427341,50.5838294]]]},"properties":{"id":"CRS3035RES200mN3077000E3815000","idInspire":"CRS3035RES200m<br />N3077000E3815000","commune":"HERLIES","people":"6","surfaceTotalPark":"","popParkIncluded":"n/a","popParkExcluded":"n/a","popSquareShare":"","squareMtePerCapita":"","surfaceTotalParkOms":"","popParkIncludedOms":"","popParkExcludedOms":"","popSquareShareOms":"","squareMtePerCapitaOms":"","commentParks":"","fillColor":"#060512","areaPerPeople":"","area":""}},{"type":"Feature","geometry":{"type":"Polygon","coordinates":[[[2.8469127,50.5750643],[2.8471859,50.5732762],[2.8499978,50.5734515],[2.8497248,50.5752396],[2.8469127,50.5750643]]]},"properties":{"id":"CRS3035RES200mN3076000E3815200","idInspire":"CRS3035RES200m<br />N3076000E3815200","commune":"HERLIES","people":"4","surfaceTotalPark":"","popParkIncluded":"n/a","popParkExcluded":"n/a","popSquareShare":"","squareMtePerCapita":"","surfaceTotalParkOms":"","popParkIncludedOms":"","popParkExcludedOms":"","popSquareShareOms":"","squareMtePerCapitaOms":"","commentParks":"","fillColor":"#060512","areaPerPeople":"","area":""}},{"type":"Feature","geometry":{"type":"Polygon","coordinates":[[[2.8525369,50.5754149],[2.8528098,50.5736268],[2.8556218,50.573802],[2.855349,50.5755901],[2.8525369,50.5754149]]]},"properties":{"id":"CRS3035RES200mN3076000E3815600","idInspire":"CRS3035RES200m<br />N3076000E3815600","commune":"HERLIES","people":"99","surfaceTotalPark":"","popParkIncluded":"n/a","popParkExcluded":"n/a","popSquareShare":"","squareMtePerCapita":"","surfaceTotalParkOms":"","popParkIncludedOms":"","popParkExcludedOms":"","popSquareShareOms":"","squareMtePerCapitaOms":"","commentParks":"","fillColor":"#060512","areaPerPeople":"","area":""}},{"type":"Feature","geometry":{"type":"Polygon","coordinates":[[[2.8548033,50.5791664],[2.8550761,50.5773783],[2.8578884,50.5775534],[2.8576156,50.5793416],[2.8548033,50.5791664]]]},"properties":{"id":"CRS3035RES200mN3076400E3815800","idInspire":"CRS3035RES200m<br />N3076400E3815800","commune":"HERLIES","people":"55","surfaceTotalPark":"","popParkIncluded":"n/a","popParkExcluded":"n/a","popSquareShare":"","squareMtePerCapita":"","surfaceTotalParkOms":"","popParkIncludedOms":"","popParkExcludedOms":"","popSquareShareOms":"","squareMtePerCapitaOms":"","commentParks":"","fillColor":"#060512","areaPerPeople":"","area":""}},{"type":"Feature","geometry":{"type":"Polygon","coordinates":[[[2.8550761,50.5773783],[2.855349,50.5755901],[2.8581611,50.5757653],[2.8578884,50.5775534],[2.8550761,50.5773783]]]},"properties":{"id":"CRS3035RES200mN3076200E3815800","idInspire":"CRS3035RES200m<br />N3076200E3815800","commune":"HERLIES","people":"116","surfaceTotalPark":"","popParkIncluded":"n/a","popParkExcluded":"n/a","popSquareShare":"","squareMtePerCapita":"","surfaceTotalParkOms":"","popParkIncludedOms":"","popParkExcludedOms":"","popSquareShareOms":"","squareMtePerCapitaOms":"","commentParks":"","fillColor":"#060512","areaPerPeople":"","area":""}},{"type":"Feature","geometry":{"type":"Polygon","coordinates":[[[2.8604279,50.5795167],[2.8607006,50.5777285],[2.8635129,50.5779035],[2.8632403,50.5796917],[2.8604279,50.5795167]]]},"properties":{"id":"CRS3035RES200mN3076400E3816200","idInspire":"CRS3035RES200m<br />N3076400E3816200","commune":"HERLIES","people":"126","surfaceTotalPark":"","popParkIncluded":"n/a","popParkExcluded":"n/a","popSquareShare":"","squareMtePerCapita":"","surfaceTotalParkOms":"","popParkIncludedOms":"","popParkExcludedOms":"","popSquareShareOms":"","squareMtePerCapitaOms":"","commentParks":"","fillColor":"#060512","areaPerPeople":"","area":""}},{"type":"Feature","geometry":{"type":"Polygon","coordinates":[[[2.8491786,50.5788159],[2.8494517,50.5770278],[2.8522639,50.577203],[2.8519909,50.5789912],[2.8491786,50.5788159]]]},"properties":{"id":"CRS3035RES200mN3076400E3815400","idInspire":"CRS3035RES200m<br />N3076400E3815400","commune":"HERLIES","people":"181","surfaceTotalPark":"","popParkIncluded":"n/a","popParkExcluded":"n/a","popSquareShare":"","squareMtePerCapita":"","surfaceTotalParkOms":"","popParkIncludedOms":"","popParkExcludedOms":"","popSquareShareOms":"","squareMtePerCapitaOms":"","commentParks":"","fillColor":"#060512","areaPerPeople":"","area":""}},{"type":"Feature","geometry":{"type":"Polygon","coordinates":[[[2.85707,50.5829179],[2.8573428,50.5811297],[2.8601552,50.5813048],[2.8598825,50.583093],[2.85707,50.5829179]]]},"properties":{"id":"CRS3035RES200mN3076800E3816000","idInspire":"CRS3035RES200m<br />N3076800E3816000","commune":"HERLIES","people":"90","surfaceTotalPark":"","popParkIncluded":"n/a","popParkExcluded":"n/a","popSquareShare":"","squareMtePerCapita":"","surfaceTotalParkOms":"","popParkIncludedOms":"","popParkExcludedOms":"","popSquareShareOms":"","squareMtePerCapitaOms":"","commentParks":"","fillColor":"#060512","areaPerPeople":"","area":""}},{"type":"Feature","geometry":{"type":"Polygon","coordinates":[[[2.8632403,50.5796917],[2.8635129,50.5779035],[2.8663251,50.5780785],[2.8660527,50.5798666],[2.8632403,50.5796917]]]},"properties":{"id":"CRS3035RES200mN3076400E3816400","idInspire":"CRS3035RES200m<br />N3076400E3816400","commune":"HERLIES","people":"4","surfaceTotalPark":"","popParkIncluded":"n/a","popParkExcluded":"n/a","popSquareShare":"","squareMtePerCapita":"","surfaceTotalParkOms":"","popParkIncludedOms":"","popParkExcludedOms":"","popSquareShareOms":"","squareMtePerCapitaOms":"","commentParks":"","fillColor":"#060512","areaPerPeople":"","area":""}},{"type":"Feature","geometry":{"type":"Polygon","coordinates":[[[2.855349,50.5755901],[2.8556218,50.573802],[2.8584338,50.5739771],[2.8581611,50.5757653],[2.855349,50.5755901]]]},"properties":{"id":"CRS3035RES200mN3076000E3815800","idInspire":"CRS3035RES200m<br />N3076000E3815800","commune":"HERLIES","people":"33","surfaceTotalPark":"","popParkIncluded":"n/a","popParkExcluded":"n/a","popSquareShare":"","squareMtePerCapita":"","surfaceTotalParkOms":"","popParkIncludedOms":"","popParkExcludedOms":"","popSquareShareOms":"","squareMtePerCapitaOms":"","commentParks":"","fillColor":"#060512","areaPerPeople":"","area":""}},{"type":"Feature","geometry":{"type":"Polygon","coordinates":[[[2.8578884,50.5775534],[2.8581611,50.5757653],[2.8609732,50.5759403],[2.8607006,50.5777285],[2.8578884,50.5775534]]]},"properties":{"id":"CRS3035RES200mN3076200E3816000","idInspire":"CRS3035RES200m<br />N3076200E3816000","commune":"HERLIES","people":"148","surfaceTotalPark":"","popParkIncluded":"n/a","popParkExcluded":"n/a","popSquareShare":"","squareMtePerCapita":"","surfaceTotalParkOms":"","popParkIncludedOms":"","popParkExcludedOms":"","popSquareShareOms":"","squareMtePerCapitaOms":"","commentParks":"","fillColor":"#060512","areaPerPeople":"","area":""}},{"type":"Feature","geometry":{"type":"Polygon","coordinates":[[[2.8460932,50.5804286],[2.8463664,50.5786405],[2.8491786,50.5788159],[2.8489055,50.580604],[2.8460932,50.5804286]]]},"properties":{"id":"CRS3035RES200mN3076600E3815200","idInspire":"CRS3035RES200m<br />N3076600E3815200","commune":"HERLIES","people":"29","surfaceTotalPark":"","popParkIncluded":"n/a","popParkExcluded":"n/a","popSquareShare":"","squareMtePerCapita":"","surfaceTotalParkOms":"","popParkIncludedOms":"","popParkExcludedOms":"","popSquareShareOms":"","squareMtePerCapitaOms":"","commentParks":"","fillColor":"#060512","areaPerPeople":"","area":""}},{"type":"Feature","geometry":{"type":"Polygon","coordinates":[[[2.8517179,50.5807793],[2.8519909,50.5789912],[2.8548033,50.5791664],[2.8545303,50.5809545],[2.8517179,50.5807793]]]},"properties":{"id":"CRS3035RES200mN3076600E3815600","idInspire":"CRS3035RES200m<br />N3076600E3815600","commune":"HERLIES","people":"82","surfaceTotalPark":"","popParkIncluded":"n/a","popParkExcluded":"n/a","popSquareShare":"","squareMtePerCapita":"","surfaceTotalParkOms":"","popParkIncludedOms":"","popParkExcludedOms":"","popSquareShareOms":"","squareMtePerCapitaOms":"","commentParks":"","fillColor":"#060512","areaPerPeople":"","area":""}},{"type":"Feature","geometry":{"type":"Polygon","coordinates":[[[2.8494517,50.5770278],[2.8497248,50.5752396],[2.8525369,50.5754149],[2.8522639,50.577203],[2.8494517,50.5770278]]]},"properties":{"id":"CRS3035RES200mN3076200E3815400","idInspire":"CRS3035RES200m<br />N3076200E3815400","commune":"HERLIES","people":"102","surfaceTotalPark":"","popParkIncluded":"n/a","popParkExcluded":"n/a","popSquareShare":"","squareMtePerCapita":"","surfaceTotalParkOms":"","popParkIncludedOms":"","popParkExcludedOms":"","popSquareShareOms":"","squareMtePerCapitaOms":"","commentParks":"","fillColor":"#060512","areaPerPeople":"","area":""}},{"type":"Feature","geometry":{"type":"Polygon","coordinates":[[[2.8497248,50.5752396],[2.8499978,50.5734515],[2.8528098,50.5736268],[2.8525369,50.5754149],[2.8497248,50.5752396]]]},"properties":{"id":"CRS3035RES200mN3076000E3815400","idInspire":"CRS3035RES200m<br />N3076000E3815400","commune":"HERLIES","people":"14","surfaceTotalPark":"","popParkIncluded":"n/a","popParkExcluded":"n/a","popSquareShare":"","squareMtePerCapita":"","surfaceTotalParkOms":"","popParkIncludedOms":"","popParkExcludedOms":"","popSquareShareOms":"","squareMtePerCapitaOms":"","commentParks":"","fillColor":"#060512","areaPerPeople":"","area":""}},{"type":"Feature","geometry":{"type":"Polygon","coordinates":[[[2.825859,50.5827752],[2.826133,50.5809872],[2.8289454,50.581163],[2.8286715,50.5829511],[2.825859,50.5827752]]]},"properties":{"id":"CRS3035RES200mN3077000E3813800","idInspire":"CRS3035RES200m<br />N3077000E3813800","commune":"HERLIES","people":"3","surfaceTotalPark":"","popParkIncluded":"n/a","popParkExcluded":"n/a","popSquareShare":"","squareMtePerCapita":"","surfaceTotalParkOms":"","popParkIncludedOms":"","popParkExcludedOms":"","popSquareShareOms":"","squareMtePerCapitaOms":"","commentParks":"","fillColor":"#060512","areaPerPeople":"","area":""}},{"type":"Feature","geometry":{"type":"Polygon","coordinates":[[[2.8486324,50.5823921],[2.8489055,50.580604],[2.8517179,50.5807793],[2.8514449,50.5825674],[2.8486324,50.5823921]]]},"properties":{"id":"CRS3035RES200mN3076800E3815400","idInspire":"CRS3035RES200m<br />N3076800E3815400","commune":"HERLIES","people":"57","surfaceTotalPark":"","popParkIncluded":"n/a","popParkExcluded":"n/a","popSquareShare":"","squareMtePerCapita":"","surfaceTotalParkOms":"","popParkIncludedOms":"","popParkExcludedOms":"","popSquareShareOms":"","squareMtePerCapitaOms":"","commentParks":"","fillColor":"#060512","areaPerPeople":"","area":""}},{"type":"Feature","geometry":{"type":"Polygon","coordinates":[[[2.8531654,50.5898952],[2.8534385,50.5881071],[2.8562513,50.5882823],[2.8559784,50.5900704],[2.8531654,50.5898952]]]},"properties":{"id":"CRS3035RES200mN3077600E3815800","idInspire":"CRS3035RES200m<br />N3077600E3815800","commune":"HERLIES","people":"2","surfaceTotalPark":"","popParkIncluded":"n/a","popParkExcluded":"n/a","popSquareShare":"","squareMtePerCapita":"","surfaceTotalParkOms":"","popParkIncludedOms":"","popParkExcludedOms":"","popSquareShareOms":"","squareMtePerCapitaOms":"","commentParks":"","fillColor":"#060512","areaPerPeople":"","area":""}},{"type":"Feature","geometry":{"type":"Polygon","coordinates":[[[2.8685927,50.5818297],[2.8688651,50.5800415],[2.8716775,50.5802163],[2.8714053,50.5820045],[2.8685927,50.5818297]]]},"properties":{"id":"CRS3035RES200mN3076600E3816800","idInspire":"CRS3035RES200m<br />N3076600E3816800","commune":"HERLIES","people":"2","surfaceTotalPark":"","popParkIncluded":"n/a","popParkExcluded":"n/a","popSquareShare":"","squareMtePerCapita":"","surfaceTotalParkOms":"","popParkIncludedOms":"","popParkExcludedOms":"","popSquareShareOms":"","squareMtePerCapitaOms":"","commentParks":"","fillColor":"#060512","areaPerPeople":"","area":""}},{"type":"Feature","geometry":{"type":"Polygon","coordinates":[[[2.8489055,50.580604],[2.8491786,50.5788159],[2.8519909,50.5789912],[2.8517179,50.5807793],[2.8489055,50.580604]]]},"properties":{"id":"CRS3035RES200mN3076600E3815400","idInspire":"CRS3035RES200m<br />N3076600E3815400","commune":"HERLIES","people":"85","surfaceTotalPark":"","popParkIncluded":"n/a","popParkExcluded":"n/a","popSquareShare":"","squareMtePerCapita":"","surfaceTotalParkOms":"","popParkIncludedOms":"","popParkExcludedOms":"","popSquareShareOms":"","squareMtePerCapitaOms":"","commentParks":"","fillColor":"#060512","areaPerPeople":"","area":""}},{"type":"Feature","geometry":{"type":"Polygon","coordinates":[[[2.8584338,50.5739771],[2.8587065,50.572189],[2.8615184,50.572364],[2.8612459,50.5741522],[2.8584338,50.5739771]]]},"properties":{"id":"CRS3035RES200mN3075800E3816000","idInspire":"CRS3035RES200m<br />N3075800E3816000","commune":"HERLIES","people":"5","surfaceTotalPark":"","popParkIncluded":"n/a","popParkExcluded":"n/a","popSquareShare":"","squareMtePerCapita":"","surfaceTotalParkOms":"","popParkIncludedOms":"","popParkExcludedOms":"","popSquareShareOms":"","squareMtePerCapitaOms":"","commentParks":"","fillColor":"#060512","areaPerPeople":"","area":""}},{"type":"Feature","geometry":{"type":"Polygon","coordinates":[[[2.8537115,50.586319],[2.8539845,50.5845308],[2.8567971,50.584706],[2.8565242,50.5864942],[2.8537115,50.586319]]]},"properties":{"id":"CRS3035RES200mN3077200E3815800","idInspire":"CRS3035RES200m<br />N3077200E3815800","commune":"HERLIES","people":"10","surfaceTotalPark":"","popParkIncluded":"n/a","popParkExcluded":"n/a","popSquareShare":"","squareMtePerCapita":"","surfaceTotalParkOms":"","popParkIncludedOms":"","popParkExcludedOms":"","popSquareShareOms":"","squareMtePerCapitaOms":"","commentParks":"","fillColor":"#060512","areaPerPeople":"","area":""}},{"type":"Feature","geometry":{"type":"Polygon","coordinates":[[[2.8511718,50.5843556],[2.8514449,50.5825674],[2.8542574,50.5827427],[2.8539845,50.5845308],[2.8511718,50.5843556]]]},"properties":{"id":"CRS3035RES200mN3077000E3815600","idInspire":"CRS3035RES200m<br />N3077000E3815600","commune":"HERLIES","people":"92","surfaceTotalPark":"","popParkIncluded":"n/a","popParkExcluded":"n/a","popSquareShare":"","squareMtePerCapita":"","surfaceTotalParkOms":"","popParkIncludedOms":"","popParkExcludedOms":"","popSquareShareOms":"","squareMtePerCapitaOms":"","commentParks":"","fillColor":"#060512","areaPerPeople":"","area":""}},{"type":"Feature","geometry":{"type":"Polygon","coordinates":[[[2.8576156,50.5793416],[2.8578884,50.5775534],[2.8607006,50.5777285],[2.8604279,50.5795167],[2.8576156,50.5793416]]]},"properties":{"id":"CRS3035RES200mN3076400E3816000","idInspire":"CRS3035RES200m<br />N3076400E3816000","commune":"HERLIES","people":"74","surfaceTotalPark":"","popParkIncluded":"n/a","popParkExcluded":"n/a","popSquareShare":"","squareMtePerCapita":"","surfaceTotalParkOms":"","popParkIncludedOms":"","popParkExcludedOms":"","popSquareShareOms":"","squareMtePerCapitaOms":"","commentParks":"","fillColor":"#060512","areaPerPeople":"","area":""}},{"type":"Feature","geometry":{"type":"Polygon","coordinates":[[[2.8657802,50.5816548],[2.8660527,50.5798666],[2.8688651,50.5800415],[2.8685927,50.5818297],[2.8657802,50.5816548]]]},"properties":{"id":"CRS3035RES200mN3076600E3816600","idInspire":"CRS3035RES200m<br />N3076600E3816600","commune":"HERLIES","people":"48","surfaceTotalPark":"","popParkIncluded":"n/a","popParkExcluded":"n/a","popSquareShare":"","squareMtePerCapita":"","surfaceTotalParkOms":"","popParkIncludedOms":"","popParkExcludedOms":"","popSquareShareOms":"","squareMtePerCapitaOms":"","commentParks":"","fillColor":"#060512","areaPerPeople":"","area":""}},{"type":"Feature","geometry":{"type":"Polygon","coordinates":[[[2.8280504,50.5684707],[2.8283242,50.5666826],[2.8311357,50.5668584],[2.830862,50.5686465],[2.8280504,50.5684707]]]},"properties":{"id":"CRS3035RES200mN3075400E3813800","idInspire":"CRS3035RES200m<br />N3075400E3813800","commune":"ILLIES","people":"2","surfaceTotalPark":"","popParkIncluded":"n/a","popParkExcluded":"n/a","popSquareShare":"","squareMtePerCapita":"","surfaceTotalParkOms":"","popParkIncludedOms":"","popParkExcludedOms":"","popSquareShareOms":"","squareMtePerCapitaOms":"","commentParks":"","fillColor":"#060512","areaPerPeople":"","area":""}},{"type":"Feature","geometry":{"type":"Polygon","coordinates":[[[2.8244169,50.573659],[2.8246909,50.5718709],[2.8275027,50.5720468],[2.8272288,50.5738349],[2.8244169,50.573659]]]},"properties":{"id":"CRS3035RES200mN3076000E3813600","idInspire":"CRS3035RES200m<br />N3076000E3813600","commune":"ILLIES","people":"23","surfaceTotalPark":"","popParkIncluded":"n/a","popParkExcluded":"n/a","popSquareShare":"","squareMtePerCapita":"","surfaceTotalParkOms":"","popParkIncludedOms":"","popParkExcludedOms":"","popSquareShareOms":"","squareMtePerCapitaOms":"","commentParks":"","fillColor":"#060512","areaPerPeople":"","area":""}},{"type":"Feature","geometry":{"type":"Polygon","coordinates":[[[2.826133,50.5809872],[2.826407,50.5791991],[2.8292193,50.5793749],[2.8289454,50.581163],[2.826133,50.5809872]]]},"properties":{"id":"CRS3035RES200mN3076800E3813800","idInspire":"CRS3035RES200m<br />N3076800E3813800","commune":"ILLIES","people":"2","surfaceTotalPark":"","popParkIncluded":"n/a","popParkExcluded":"n/a","popSquareShare":"","squareMtePerCapita":"","surfaceTotalParkOms":"","popParkIncludedOms":"","popParkExcludedOms":"","popSquareShareOms":"","squareMtePerCapitaOms":"","commentParks":"","fillColor":"#060512","areaPerPeople":"","area":""}},{"type":"Feature","geometry":{"type":"Polygon","coordinates":[[[2.828598,50.5648945],[2.8288717,50.5631065],[2.831683,50.5632822],[2.8314094,50.5650703],[2.828598,50.5648945]]]},"properties":{"id":"CRS3035RES200mN3075000E3813800","idInspire":"CRS3035RES200m<br />N3075000E3813800","commune":"ILLIES","people":"71","surfaceTotalPark":"","popParkIncluded":"n/a","popParkExcluded":"n/a","popSquareShare":"","squareMtePerCapita":"","surfaceTotalParkOms":"","popParkIncludedOms":"","popParkExcludedOms":"","popSquareShareOms":"","squareMtePerCapitaOms":"","commentParks":"","fillColor":"#060512","areaPerPeople":"","area":""}},{"type":"Feature","geometry":{"type":"Polygon","coordinates":[[[2.8233207,50.5808112],[2.8235948,50.5790232],[2.826407,50.5791991],[2.826133,50.5809872],[2.8233207,50.5808112]]]},"properties":{"id":"CRS3035RES200mN3076800E3813600","idInspire":"CRS3035RES200m<br />N3076800E3813600","commune":"ILLIES","people":"2","surfaceTotalPark":"","popParkIncluded":"n/a","popParkExcluded":"n/a","popSquareShare":"","squareMtePerCapita":"","surfaceTotalParkOms":"","popParkIncludedOms":"","popParkExcludedOms":"","popSquareShareOms":"","squareMtePerCapitaOms":"","commentParks":"","fillColor":"#060512","areaPerPeople":"","area":""}},{"type":"Feature","geometry":{"type":"Polygon","coordinates":[[[2.8238689,50.5772351],[2.8241429,50.5754471],[2.8269549,50.575623],[2.826681,50.577411],[2.8238689,50.5772351]]]},"properties":{"id":"CRS3035RES200mN3076400E3813600","idInspire":"CRS3035RES200m<br />N3076400E3813600","commune":"ILLIES","people":"18","surfaceTotalPark":"","popParkIncluded":"n/a","popParkExcluded":"n/a","popSquareShare":"","squareMtePerCapita":"","surfaceTotalParkOms":"","popParkIncludedOms":"","popParkExcludedOms":"","popSquareShareOms":"","squareMtePerCapitaOms":"","commentParks":"","fillColor":"#060512","areaPerPeople":"","area":""}},{"type":"Feature","geometry":{"type":"Polygon","coordinates":[[[2.8255127,50.5665067],[2.8257866,50.5647187],[2.828598,50.5648945],[2.8283242,50.5666826],[2.8255127,50.5665067]]]},"properties":{"id":"CRS3035RES200mN3075200E3813600","idInspire":"CRS3035RES200m<br />N3075200E3813600","commune":"ILLIES","people":"4","surfaceTotalPark":"","popParkIncluded":"n/a","popParkExcluded":"n/a","popSquareShare":"","squareMtePerCapita":"","surfaceTotalParkOms":"","popParkIncludedOms":"","popParkExcludedOms":"","popSquareShareOms":"","squareMtePerCapitaOms":"","commentParks":"","fillColor":"#060512","areaPerPeople":"","area":""}},{"type":"Feature","geometry":{"type":"Polygon","coordinates":[[[2.8314094,50.5650703],[2.831683,50.5632822],[2.8344943,50.563458],[2.8342208,50.5652461],[2.8314094,50.5650703]]]},"properties":{"id":"CRS3035RES200mN3075000E3814000","idInspire":"CRS3035RES200m<br />N3075000E3814000","commune":"ILLIES","people":"3","surfaceTotalPark":"","popParkIncluded":"n/a","popParkExcluded":"n/a","popSquareShare":"","squareMtePerCapita":"","surfaceTotalParkOms":"","popParkIncludedOms":"","popParkExcludedOms":"","popSquareShareOms":"","squareMtePerCapitaOms":"","commentParks":"","fillColor":"#060512","areaPerPeople":"","area":""}},{"type":"Feature","geometry":{"type":"Polygon","coordinates":[[[2.826407,50.5791991],[2.826681,50.577411],[2.8294931,50.5775869],[2.8292193,50.5793749],[2.826407,50.5791991]]]},"properties":{"id":"CRS3035RES200mN3076600E3813800","idInspire":"CRS3035RES200m<br />N3076600E3813800","commune":"ILLIES","people":"15","surfaceTotalPark":"","popParkIncluded":"n/a","popParkExcluded":"n/a","popSquareShare":"","squareMtePerCapita":"","surfaceTotalParkOms":"","popParkIncludedOms":"","popParkExcludedOms":"","popSquareShareOms":"","squareMtePerCapitaOms":"","commentParks":"","fillColor":"#060512","areaPerPeople":"","area":""}},{"type":"Feature","geometry":{"type":"Polygon","coordinates":[[[2.8235948,50.5790232],[2.8238689,50.5772351],[2.826681,50.577411],[2.826407,50.5791991],[2.8235948,50.5790232]]]},"properties":{"id":"CRS3035RES200mN3076600E3813600","idInspire":"CRS3035RES200m<br />N3076600E3813600","commune":"ILLIES","people":"14","surfaceTotalPark":"","popParkIncluded":"n/a","popParkExcluded":"n/a","popSquareShare":"","squareMtePerCapita":"","surfaceTotalParkOms":"","popParkIncludedOms":"","popParkExcludedOms":"","popSquareShareOms":"","squareMtePerCapitaOms":"","commentParks":"","fillColor":"#060512","areaPerPeople":"","area":""}},{"type":"Feature","geometry":{"type":"Polygon","coordinates":[[[2.8249649,50.5700829],[2.8252388,50.5682948],[2.8280504,50.5684707],[2.8277766,50.5702588],[2.8249649,50.5700829]]]},"properties":{"id":"CRS3035RES200mN3075600E3813600","idInspire":"CRS3035RES200m<br />N3075600E3813600","commune":"ILLIES","people":"1","surfaceTotalPark":"","popParkIncluded":"n/a","popParkExcluded":"n/a","popSquareShare":"","squareMtePerCapita":"","surfaceTotalParkOms":"","popParkIncludedOms":"","popParkExcludedOms":"","popSquareShareOms":"","squareMtePerCapitaOms":"","commentParks":"","fillColor":"#060512","areaPerPeople":"","area":""}},{"type":"Feature","geometry":{"type":"Polygon","coordinates":[[[2.826681,50.577411],[2.8269549,50.575623],[2.829767,50.5757988],[2.8294931,50.5775869],[2.826681,50.577411]]]},"properties":{"id":"CRS3035RES200mN3076400E3813800","idInspire":"CRS3035RES200m<br />N3076400E3813800","commune":"ILLIES","people":"37","surfaceTotalPark":"","popParkIncluded":"n/a","popParkExcluded":"n/a","popSquareShare":"","squareMtePerCapita":"","surfaceTotalParkOms":"","popParkIncludedOms":"","popParkExcludedOms":"","popSquareShareOms":"","squareMtePerCapitaOms":"","commentParks":"","fillColor":"#060512","areaPerPeople":"","area":""}},{"type":"Feature","geometry":{"type":"Polygon","coordinates":[[[2.8283242,50.5666826],[2.828598,50.5648945],[2.8314094,50.5650703],[2.8311357,50.5668584],[2.8283242,50.5666826]]]},"properties":{"id":"CRS3035RES200mN3075200E3813800","idInspire":"CRS3035RES200m<br />N3075200E3813800","commune":"ILLIES","people":"14","surfaceTotalPark":"","popParkIncluded":"n/a","popParkExcluded":"n/a","popSquareShare":"","squareMtePerCapita":"","surfaceTotalParkOms":"","popParkIncludedOms":"","popParkExcludedOms":"","popSquareShareOms":"","squareMtePerCapitaOms":"","commentParks":"","fillColor":"#060512","areaPerPeople":"","area":""}},{"type":"Feature","geometry":{"type":"Polygon","coordinates":[[[2.8257866,50.5647187],[2.8260605,50.5629306],[2.8288717,50.5631065],[2.828598,50.5648945],[2.8257866,50.5647187]]]},"properties":{"id":"CRS3035RES200mN3075000E3813600","idInspire":"CRS3035RES200m<br />N3075000E3813600","commune":"ILLIES","people":"5","surfaceTotalPark":"","popParkIncluded":"n/a","popParkExcluded":"n/a","popSquareShare":"","squareMtePerCapita":"","surfaceTotalParkOms":"","popParkIncludedOms":"","popParkExcludedOms":"","popSquareShareOms":"","squareMtePerCapitaOms":"","commentParks":"","fillColor":"#060512","areaPerPeople":"","area":""}},{"type":"Feature","geometry":{"type":"Polygon","coordinates":[[[2.8246909,50.5718709],[2.8249649,50.5700829],[2.8277766,50.5702588],[2.8275027,50.5720468],[2.8246909,50.5718709]]]},"properties":{"id":"CRS3035RES200mN3075800E3813600","idInspire":"CRS3035RES200m<br />N3075800E3813600","commune":"ILLIES","people":"16","surfaceTotalPark":"","popParkIncluded":"n/a","popParkExcluded":"n/a","popSquareShare":"","squareMtePerCapita":"","surfaceTotalParkOms":"","popParkIncludedOms":"","popParkExcludedOms":"","popSquareShareOms":"","squareMtePerCapitaOms":"","commentParks":"","fillColor":"#060512","areaPerPeople":"","area":""}},{"type":"Feature","geometry":{"type":"Polygon","coordinates":[[[2.8699543,50.5728888],[2.8702266,50.5711006],[2.8730385,50.5712754],[2.8727663,50.5730636],[2.8699543,50.5728888]]]},"properties":{"id":"CRS3035RES200mN3075600E3816800","idInspire":"CRS3035RES200m<br />N3075600E3816800","commune":"WICRES","people":"14","surfaceTotalPark":"","popParkIncluded":"n/a","popParkExcluded":"n/a","popSquareShare":"","squareMtePerCapita":"","surfaceTotalParkOms":"","popParkIncludedOms":"","popParkExcludedOms":"","popSquareShareOms":"","squareMtePerCapitaOms":"","commentParks":"","fillColor":"#060512","areaPerPeople":"","area":""}},{"type":"Feature","geometry":{"type":"Polygon","coordinates":[[[2.861791,50.5705759],[2.8620635,50.5687877],[2.8648753,50.5689627],[2.8646028,50.5707508],[2.861791,50.5705759]]]},"properties":{"id":"CRS3035RES200mN3075400E3816200","idInspire":"CRS3035RES200m<br />N3075400E3816200","commune":"WICRES","people":"3","surfaceTotalPark":"","popParkIncluded":"n/a","popParkExcluded":"n/a","popSquareShare":"","squareMtePerCapita":"","surfaceTotalParkOms":"","popParkIncludedOms":"","popParkExcludedOms":"","popSquareShareOms":"","squareMtePerCapitaOms":"","commentParks":"","fillColor":"#060512","areaPerPeople":"","area":""}},{"type":"Feature","geometry":{"type":"Polygon","coordinates":[[[2.8671424,50.5727139],[2.8674147,50.5709258],[2.8702266,50.5711006],[2.8699543,50.5728888],[2.8671424,50.5727139]]]},"properties":{"id":"CRS3035RES200mN3075600E3816600","idInspire":"CRS3035RES200m<br />N3075600E3816600","commune":"WICRES","people":"134","surfaceTotalPark":"","popParkIncluded":"n/a","popParkExcluded":"n/a","popSquareShare":"","squareMtePerCapita":"","surfaceTotalParkOms":"","popParkIncludedOms":"","popParkExcludedOms":"","popSquareShareOms":"","squareMtePerCapitaOms":"","commentParks":"","fillColor":"#060512","areaPerPeople":"","area":""}},{"type":"Feature","geometry":{"type":"Polygon","coordinates":[[[2.8674147,50.5709258],[2.867687,50.5691376],[2.8704988,50.5693124],[2.8702266,50.5711006],[2.8674147,50.5709258]]]},"properties":{"id":"CRS3035RES200mN3075400E3816600","idInspire":"CRS3035RES200m<br />N3075400E3816600","commune":"WICRES","people":"8","surfaceTotalPark":"","popParkIncluded":"n/a","popParkExcluded":"n/a","popSquareShare":"","squareMtePerCapita":"","surfaceTotalParkOms":"","popParkIncludedOms":"","popParkExcludedOms":"","popSquareShareOms":"","squareMtePerCapitaOms":"","commentParks":"","fillColor":"#060512","areaPerPeople":"","area":""}},{"type":"Feature","geometry":{"type":"Polygon","coordinates":[[[2.8643304,50.572539],[2.8646028,50.5707508],[2.8674147,50.5709258],[2.8671424,50.5727139],[2.8643304,50.572539]]]},"properties":{"id":"CRS3035RES200mN3075600E3816400","idInspire":"CRS3035RES200m<br />N3075600E3816400","commune":"WICRES","people":"102","surfaceTotalPark":"","popParkIncluded":"n/a","popParkExcluded":"n/a","popSquareShare":"","squareMtePerCapita":"","surfaceTotalParkOms":"","popParkIncludedOms":"","popParkExcludedOms":"","popSquareShareOms":"","squareMtePerCapitaOms":"","commentParks":"","fillColor":"#060512","areaPerPeople":"","area":""}},{"type":"Feature","geometry":{"type":"Polygon","coordinates":[[[2.8567128,50.5666494],[2.8569855,50.5648612],[2.859797,50.5650363],[2.8595244,50.5668245],[2.8567128,50.5666494]]]},"properties":{"id":"CRS3035RES200mN3075000E3815800","idInspire":"CRS3035RES200m<br />N3075000E3815800","commune":"WICRES","people":"1","surfaceTotalPark":"","popParkIncluded":"n/a","popParkExcluded":"n/a","popSquareShare":"","squareMtePerCapita":"","surfaceTotalParkOms":"","popParkIncludedOms":"","popParkExcludedOms":"","popSquareShareOms":"","squareMtePerCapitaOms":"","commentParks":"","fillColor":"#060512","areaPerPeople":"","area":""}},{"type":"Feature","geometry":{"type":"Polygon","coordinates":[[[2.8620635,50.5687877],[2.862336,50.5669995],[2.8651477,50.5671745],[2.8648753,50.5689627],[2.8620635,50.5687877]]]},"properties":{"id":"CRS3035RES200mN3075200E3816200","idInspire":"CRS3035RES200m<br />N3075200E3816200","commune":"WICRES","people":"11","surfaceTotalPark":"","popParkIncluded":"n/a","popParkExcluded":"n/a","popSquareShare":"","squareMtePerCapita":"","surfaceTotalParkOms":"","popParkIncludedOms":"","popParkExcludedOms":"","popSquareShareOms":"","squareMtePerCapitaOms":"","commentParks":"","fillColor":"#060512","areaPerPeople":"","area":""}},{"type":"Feature","geometry":{"type":"Polygon","coordinates":[[[2.8696821,50.574677],[2.8699543,50.5728888],[2.8727663,50.5730636],[2.8724942,50.5748518],[2.8696821,50.574677]]]},"properties":{"id":"CRS3035RES200mN3075800E3816800","idInspire":"CRS3035RES200m<br />N3075800E3816800","commune":"WICRES","people":"23","surfaceTotalPark":"","popParkIncluded":"n/a","popParkExcluded":"n/a","popSquareShare":"","squareMtePerCapita":"","surfaceTotalParkOms":"","popParkIncludedOms":"","popParkExcludedOms":"","popSquareShareOms":"","squareMtePerCapitaOms":"","commentParks":"","fillColor":"#060512","areaPerPeople":"","area":""}},{"type":"Feature","geometry":{"type":"Polygon","coordinates":[[[2.8595244,50.5668245],[2.859797,50.5650363],[2.8626085,50.5652114],[2.862336,50.5669995],[2.8595244,50.5668245]]]},"properties":{"id":"CRS3035RES200mN3075000E3816000","idInspire":"CRS3035RES200m<br />N3075000E3816000","commune":"WICRES","people":"17","surfaceTotalPark":"","popParkIncluded":"n/a","popParkExcluded":"n/a","popSquareShare":"","squareMtePerCapita":"","surfaceTotalParkOms":"","popParkIncludedOms":"","popParkExcludedOms":"","popSquareShareOms":"","squareMtePerCapitaOms":"","commentParks":"","fillColor":"#060512","areaPerPeople":"","area":""}},{"type":"Feature","geometry":{"type":"Polygon","coordinates":[[[2.8646028,50.5707508],[2.8648753,50.5689627],[2.867687,50.5691376],[2.8674147,50.5709258],[2.8646028,50.5707508]]]},"properties":{"id":"CRS3035RES200mN3075400E3816400","idInspire":"CRS3035RES200m<br />N3075400E3816400","commune":"WICRES","people":"32","surfaceTotalPark":"","popParkIncluded":"n/a","popParkExcluded":"n/a","popSquareShare":"","squareMtePerCapita":"","surfaceTotalParkOms":"","popParkIncludedOms":"","popParkExcludedOms":"","popSquareShareOms":"","squareMtePerCapitaOms":"","commentParks":"","fillColor":"#060512","areaPerPeople":"","area":""}},{"type":"Feature","geometry":{"type":"Polygon","coordinates":[[[2.8615184,50.572364],[2.861791,50.5705759],[2.8646028,50.5707508],[2.8643304,50.572539],[2.8615184,50.572364]]]},"properties":{"id":"CRS3035RES200mN3075600E3816200","idInspire":"CRS3035RES200m<br />N3075600E3816200","commune":"WICRES","people":"21","surfaceTotalPark":"","popParkIncluded":"n/a","popParkExcluded":"n/a","popSquareShare":"","squareMtePerCapita":"","surfaceTotalParkOms":"","popParkIncludedOms":"","popParkExcludedOms":"","popSquareShareOms":"","squareMtePerCapitaOms":"","commentParks":"","fillColor":"#060512","areaPerPeople":"","area":""}},{"type":"Feature","geometry":{"type":"Polygon","coordinates":[[[2.86687,50.5745021],[2.8671424,50.5727139],[2.8699543,50.5728888],[2.8696821,50.574677],[2.86687,50.5745021]]]},"properties":{"id":"CRS3035RES200mN3075800E3816600","idInspire":"CRS3035RES200m<br />N3075800E3816600","commune":"WICRES","people":"128","surfaceTotalPark":"","popParkIncluded":"n/a","popParkExcluded":"n/a","popSquareShare":"","squareMtePerCapita":"","surfaceTotalParkOms":"","popParkIncludedOms":"","popParkExcludedOms":"","popSquareShareOms":"","squareMtePerCapitaOms":"","commentParks":"","fillColor":"#060512","areaPerPeople":"","area":""}},{"type":"Feature","geometry":{"type":"Polygon","coordinates":[[[2.8626085,50.5652114],[2.862881,50.5634232],[2.8656924,50.5635981],[2.8654201,50.5653863],[2.8626085,50.5652114]]]},"properties":{"id":"CRS3035RES200mN3074800E3816200","idInspire":"CRS3035RES200m<br />N3074800E3816200","commune":"MARQUILLIES","people":"10","surfaceTotalPark":"","popParkIncluded":"n/a","popParkExcluded":"n/a","popSquareShare":"","squareMtePerCapita":"","surfaceTotalParkOms":"","popParkIncludedOms":"","popParkExcludedOms":"","popSquareShareOms":"","squareMtePerCapitaOms":"","commentParks":"","fillColor":"#060512","areaPerPeople":"","area":""}},{"type":"Feature","geometry":{"type":"Polygon","coordinates":[[[2.8410933,50.594558],[2.8413668,50.5927699],[2.8441799,50.5929454],[2.8439065,50.5947335],[2.8410933,50.594558]]]},"properties":{"id":"CRS3035RES200mN3078200E3815000","idInspire":"CRS3035RES200m<br />N3078200E3815000","commune":"AUBERS","people":"2","surfaceTotalPark":"","popParkIncluded":"n/a","popParkExcluded":"n/a","popSquareShare":"","squareMtePerCapita":"","surfaceTotalParkOms":"","popParkIncludedOms":"","popParkExcludedOms":"","popSquareShareOms":"","squareMtePerCapitaOms":"","commentParks":"","fillColor":"#060512","areaPerPeople":"","area":""}},{"type":"Feature","geometry":{"type":"Polygon","coordinates":[[[2.823666,50.5970796],[2.8239402,50.5952916],[2.8267534,50.5954675],[2.8264793,50.5972556],[2.823666,50.5970796]]]},"properties":{"id":"CRS3035RES200mN3078600E3813800","idInspire":"CRS3035RES200m<br />N3078600E3813800","commune":"AUBERS","people":"88","surfaceTotalPark":"","popParkIncluded":"n/a","popParkExcluded":"n/a","popSquareShare":"","squareMtePerCapita":"","surfaceTotalParkOms":"","popParkIncludedOms":"","popParkExcludedOms":"","popSquareShareOms":"","squareMtePerCapitaOms":"","commentParks":"","fillColor":"#060512","areaPerPeople":"","area":""}},{"type":"Feature","geometry":{"type":"Polygon","coordinates":[[[2.8318321,50.5993953],[2.832106,50.5976072],[2.8349193,50.5977829],[2.8346455,50.599571],[2.8318321,50.5993953]]]},"properties":{"id":"CRS3035RES200mN3078800E3814400","idInspire":"CRS3035RES200m<br />N3078800E3814400","commune":"AUBERS","people":"92","surfaceTotalPark":"","popParkIncluded":"n/a","popParkExcluded":"n/a","popSquareShare":"","squareMtePerCapita":"","surfaceTotalParkOms":"","popParkIncludedOms":"","popParkExcludedOms":"","popSquareShareOms":"","squareMtePerCapitaOms":"","commentParks":"","fillColor":"#060512","areaPerPeople":"","area":""}},{"type":"Feature","geometry":{"type":"Polygon","coordinates":[[[2.8380064,50.5961705],[2.8382801,50.5943824],[2.8410933,50.594558],[2.8408197,50.5963461],[2.8380064,50.5961705]]]},"properties":{"id":"CRS3035RES200mN3078400E3814800","idInspire":"CRS3035RES200m<br />N3078400E3814800","commune":"AUBERS","people":"5","surfaceTotalPark":"","popParkIncluded":"n/a","popParkExcluded":"n/a","popSquareShare":"","squareMtePerCapita":"","surfaceTotalParkOms":"","popParkIncludedOms":"","popParkExcludedOms":"","popSquareShareOms":"","squareMtePerCapitaOms":"","commentParks":"","fillColor":"#060512","areaPerPeople":"","area":""}},{"type":"Feature","geometry":{"type":"Polygon","coordinates":[[[2.8270275,50.5936795],[2.8273016,50.5918914],[2.8301146,50.5920672],[2.8298406,50.5938553],[2.8270275,50.5936795]]]},"properties":{"id":"CRS3035RES200mN3078200E3814000","idInspire":"CRS3035RES200m<br />N3078200E3814000","commune":"AUBERS","people":"2","surfaceTotalPark":"","popParkIncluded":"n/a","popParkExcluded":"n/a","popSquareShare":"","squareMtePerCapita":"","surfaceTotalParkOms":"","popParkIncludedOms":"","popParkExcludedOms":"","popSquareShareOms":"","squareMtePerCapitaOms":"","commentParks":"","fillColor":"#060512","areaPerPeople":"","area":""}},{"type":"Feature","geometry":{"type":"Polygon","coordinates":[[[2.8323799,50.5958192],[2.8326538,50.5940311],[2.8354669,50.5942068],[2.8351931,50.5959949],[2.8323799,50.5958192]]]},"properties":{"id":"CRS3035RES200mN3078400E3814400","idInspire":"CRS3035RES200m<br />N3078400E3814400","commune":"AUBERS","people":"9","surfaceTotalPark":"","popParkIncluded":"n/a","popParkExcluded":"n/a","popSquareShare":"","squareMtePerCapita":"","surfaceTotalParkOms":"","popParkIncludedOms":"","popParkExcludedOms":"","popSquareShareOms":"","squareMtePerCapitaOms":"","commentParks":"","fillColor":"#060512","areaPerPeople":"","area":""}},{"type":"Feature","geometry":{"type":"Polygon","coordinates":[[[2.8351931,50.5959949],[2.8354669,50.5942068],[2.8382801,50.5943824],[2.8380064,50.5961705],[2.8351931,50.5959949]]]},"properties":{"id":"CRS3035RES200mN3078400E3814600","idInspire":"CRS3035RES200m<br />N3078400E3814600","commune":"AUBERS","people":"14","surfaceTotalPark":"","popParkIncluded":"n/a","popParkExcluded":"n/a","popSquareShare":"","squareMtePerCapita":"","surfaceTotalParkOms":"","popParkIncludedOms":"","popParkExcludedOms":"","popSquareShareOms":"","squareMtePerCapitaOms":"","commentParks":"","fillColor":"#060512","areaPerPeople":"","area":""}},{"type":"Feature","geometry":{"type":"Polygon","coordinates":[[[2.8239402,50.5952916],[2.8242144,50.5935035],[2.8270275,50.5936795],[2.8267534,50.5954675],[2.8239402,50.5952916]]]},"properties":{"id":"CRS3035RES200mN3078400E3813800","idInspire":"CRS3035RES200m<br />N3078400E3813800","commune":"AUBERS","people":"67","surfaceTotalPark":"","popParkIncluded":"n/a","popParkExcluded":"n/a","popSquareShare":"","squareMtePerCapita":"","surfaceTotalParkOms":"","popParkIncludedOms":"","popParkExcludedOms":"","popSquareShareOms":"","squareMtePerCapitaOms":"","commentParks":"","fillColor":"#060512","areaPerPeople":"","area":""}},{"type":"Feature","geometry":{"type":"Polygon","coordinates":[[[2.8290186,50.5992195],[2.8292926,50.5974314],[2.832106,50.5976072],[2.8318321,50.5993953],[2.8290186,50.5992195]]]},"properties":{"id":"CRS3035RES200mN3078800E3814200","idInspire":"CRS3035RES200m<br />N3078800E3814200","commune":"AUBERS","people":"81","surfaceTotalPark":"","popParkIncluded":"n/a","popParkExcluded":"n/a","popSquareShare":"","squareMtePerCapita":"","surfaceTotalParkOms":"","popParkIncludedOms":"","popParkExcludedOms":"","popSquareShareOms":"","squareMtePerCapitaOms":"","commentParks":"","fillColor":"#060512","areaPerPeople":"","area":""}},{"type":"Feature","geometry":{"type":"Polygon","coordinates":[[[2.8382801,50.5943824],[2.8385537,50.5925943],[2.8413668,50.5927699],[2.8410933,50.594558],[2.8382801,50.5943824]]]},"properties":{"id":"CRS3035RES200mN3078200E3814800","idInspire":"CRS3035RES200m<br />N3078200E3814800","commune":"AUBERS","people":"5","surfaceTotalPark":"","popParkIncluded":"n/a","popParkExcluded":"n/a","popSquareShare":"","squareMtePerCapita":"","surfaceTotalParkOms":"","popParkIncludedOms":"","popParkExcludedOms":"","popSquareShareOms":"","squareMtePerCapitaOms":"","commentParks":"","fillColor":"#060512","areaPerPeople":"","area":""}},{"type":"Feature","geometry":{"type":"Polygon","coordinates":[[[2.8242144,50.5935035],[2.8244886,50.5917155],[2.8273016,50.5918914],[2.8270275,50.5936795],[2.8242144,50.5935035]]]},"properties":{"id":"CRS3035RES200mN3078200E3813800","idInspire":"CRS3035RES200m<br />N3078200E3813800","commune":"AUBERS","people":"0","surfaceTotalPark":"","popParkIncluded":"n/a","popParkExcluded":"n/a","popSquareShare":"","squareMtePerCapita":"","surfaceTotalParkOms":"","popParkIncludedOms":"","popParkExcludedOms":"","popSquareShareOms":"","squareMtePerCapitaOms":"","commentParks":"","fillColor":"#060512","areaPerPeople":"","area":""}},{"type":"Feature","geometry":{"type":"Polygon","coordinates":[[[2.8262052,50.5990436],[2.8264793,50.5972556],[2.8292926,50.5974314],[2.8290186,50.5992195],[2.8262052,50.5990436]]]},"properties":{"id":"CRS3035RES200mN3078800E3814000","idInspire":"CRS3035RES200m<br />N3078800E3814000","commune":"AUBERS","people":"19","surfaceTotalPark":"","popParkIncluded":"n/a","popParkExcluded":"n/a","popSquareShare":"","squareMtePerCapita":"","surfaceTotalParkOms":"","popParkIncludedOms":"","popParkExcludedOms":"","popSquareShareOms":"","squareMtePerCapitaOms":"","commentParks":"","fillColor":"#060512","areaPerPeople":"","area":""}},{"type":"Feature","geometry":{"type":"Polygon","coordinates":[[[2.8233918,50.5988677],[2.823666,50.5970796],[2.8264793,50.5972556],[2.8262052,50.5990436],[2.8233918,50.5988677]]]},"properties":{"id":"CRS3035RES200mN3078800E3813800","idInspire":"CRS3035RES200m<br />N3078800E3813800","commune":"AUBERS","people":"1","surfaceTotalPark":"","popParkIncluded":"n/a","popParkExcluded":"n/a","popSquareShare":"","squareMtePerCapita":"","surfaceTotalParkOms":"","popParkIncludedOms":"","popParkExcludedOms":"","popSquareShareOms":"","squareMtePerCapitaOms":"","commentParks":"","fillColor":"#060512","areaPerPeople":"","area":""}},{"type":"Feature","geometry":{"type":"Polygon","coordinates":[[[2.8329276,50.592243],[2.8332014,50.5904549],[2.8360144,50.5906306],[2.8357406,50.5924187],[2.8329276,50.592243]]]},"properties":{"id":"CRS3035RES200mN3078000E3814400","idInspire":"CRS3035RES200m<br />N3078000E3814400","commune":"AUBERS","people":"5","surfaceTotalPark":"","popParkIncluded":"n/a","popParkExcluded":"n/a","popSquareShare":"","squareMtePerCapita":"","surfaceTotalParkOms":"","popParkIncludedOms":"","popParkExcludedOms":"","popSquareShareOms":"","squareMtePerCapitaOms":"","commentParks":"","fillColor":"#060512","areaPerPeople":"","area":""}},{"type":"Feature","geometry":{"type":"Polygon","coordinates":[[[2.8354669,50.5942068],[2.8357406,50.5924187],[2.8385537,50.5925943],[2.8382801,50.5943824],[2.8354669,50.5942068]]]},"properties":{"id":"CRS3035RES200mN3078200E3814600","idInspire":"CRS3035RES200m<br />N3078200E3814600","commune":"AUBERS","people":"10","surfaceTotalPark":"","popParkIncluded":"n/a","popParkExcluded":"n/a","popSquareShare":"","squareMtePerCapita":"","surfaceTotalParkOms":"","popParkIncludedOms":"","popParkExcludedOms":"","popSquareShareOms":"","squareMtePerCapitaOms":"","commentParks":"","fillColor":"#060512","areaPerPeople":"","area":""}},{"type":"Feature","geometry":{"type":"Polygon","coordinates":[[[2.8332014,50.5904549],[2.8334752,50.5886669],[2.8362881,50.5888425],[2.8360144,50.5906306],[2.8332014,50.5904549]]]},"properties":{"id":"CRS3035RES200mN3077800E3814400","idInspire":"CRS3035RES200m<br />N3077800E3814400","commune":"AUBERS","people":"1","surfaceTotalPark":"","popParkIncluded":"n/a","popParkExcluded":"n/a","popSquareShare":"","squareMtePerCapita":"","surfaceTotalParkOms":"","popParkIncludedOms":"","popParkExcludedOms":"","popSquareShareOms":"","squareMtePerCapitaOms":"","commentParks":"","fillColor":"#060512","areaPerPeople":"","area":""}},{"type":"Feature","geometry":{"type":"Polygon","coordinates":[[[2.8292926,50.5974314],[2.8295666,50.5956434],[2.8323799,50.5958192],[2.832106,50.5976072],[2.8292926,50.5974314]]]},"properties":{"id":"CRS3035RES200mN3078600E3814200","idInspire":"CRS3035RES200m<br />N3078600E3814200","commune":"AUBERS","people":"74","surfaceTotalPark":"","popParkIncluded":"n/a","popParkExcluded":"n/a","popSquareShare":"","squareMtePerCapita":"","surfaceTotalParkOms":"","popParkIncludedOms":"","popParkExcludedOms":"","popSquareShareOms":"","squareMtePerCapitaOms":"","commentParks":"","fillColor":"#060512","areaPerPeople":"","area":""}},{"type":"Feature","geometry":{"type":"Polygon","coordinates":[[[2.8267534,50.5954675],[2.8270275,50.5936795],[2.8298406,50.5938553],[2.8295666,50.5956434],[2.8267534,50.5954675]]]},"properties":{"id":"CRS3035RES200mN3078400E3814000","idInspire":"CRS3035RES200m<br />N3078400E3814000","commune":"AUBERS","people":"54","surfaceTotalPark":"","popParkIncluded":"n/a","popParkExcluded":"n/a","popSquareShare":"","squareMtePerCapita":"","surfaceTotalParkOms":"","popParkIncludedOms":"","popParkExcludedOms":"","popSquareShareOms":"","squareMtePerCapitaOms":"","commentParks":"","fillColor":"#060512","areaPerPeople":"","area":""}},{"type":"Feature","geometry":{"type":"Polygon","coordinates":[[[2.8334752,50.5886669],[2.833749,50.5868788],[2.8365617,50.5870545],[2.8362881,50.5888425],[2.8334752,50.5886669]]]},"properties":{"id":"CRS3035RES200mN3077600E3814400","idInspire":"CRS3035RES200m<br />N3077600E3814400","commune":"AUBERS","people":"1","surfaceTotalPark":"","popParkIncluded":"n/a","popParkExcluded":"n/a","popSquareShare":"","squareMtePerCapita":"","surfaceTotalParkOms":"","popParkIncludedOms":"","popParkExcludedOms":"","popSquareShareOms":"","squareMtePerCapitaOms":"","commentParks":"","fillColor":"#060512","areaPerPeople":"","area":""}},{"type":"Feature","geometry":{"type":"Polygon","coordinates":[[[2.832106,50.5976072],[2.8323799,50.5958192],[2.8351931,50.5959949],[2.8349193,50.5977829],[2.832106,50.5976072]]]},"properties":{"id":"CRS3035RES200mN3078600E3814400","idInspire":"CRS3035RES200m<br />N3078600E3814400","commune":"AUBERS","people":"3","surfaceTotalPark":"","popParkIncluded":"n/a","popParkExcluded":"n/a","popSquareShare":"","squareMtePerCapita":"","surfaceTotalParkOms":"","popParkIncludedOms":"","popParkExcludedOms":"","popSquareShareOms":"","squareMtePerCapitaOms":"","commentParks":"","fillColor":"#060512","areaPerPeople":"","area":""}},{"type":"Feature","geometry":{"type":"Polygon","coordinates":[[[2.8326538,50.5940311],[2.8329276,50.592243],[2.8357406,50.5924187],[2.8354669,50.5942068],[2.8326538,50.5940311]]]},"properties":{"id":"CRS3035RES200mN3078200E3814400","idInspire":"CRS3035RES200m<br />N3078200E3814400","commune":"AUBERS","people":"2","surfaceTotalPark":"","popParkIncluded":"n/a","popParkExcluded":"n/a","popSquareShare":"","squareMtePerCapita":"","surfaceTotalParkOms":"","popParkIncludedOms":"","popParkExcludedOms":"","popSquareShareOms":"","squareMtePerCapitaOms":"","commentParks":"","fillColor":"#060512","areaPerPeople":"","area":""}},{"type":"Feature","geometry":{"type":"Polygon","coordinates":[[[2.8357406,50.5924187],[2.8360144,50.5906306],[2.8388273,50.5908063],[2.8385537,50.5925943],[2.8357406,50.5924187]]]},"properties":{"id":"CRS3035RES200mN3078000E3814600","idInspire":"CRS3035RES200m<br />N3078000E3814600","commune":"AUBERS","people":"4","surfaceTotalPark":"","popParkIncluded":"n/a","popParkExcluded":"n/a","popSquareShare":"","squareMtePerCapita":"","surfaceTotalParkOms":"","popParkIncludedOms":"","popParkExcludedOms":"","popSquareShareOms":"","squareMtePerCapitaOms":"","commentParks":"","fillColor":"#060512","areaPerPeople":"","area":""}},{"type":"Feature","geometry":{"type":"Polygon","coordinates":[[[2.8301146,50.5920672],[2.8303885,50.5902792],[2.8332014,50.5904549],[2.8329276,50.592243],[2.8301146,50.5920672]]]},"properties":{"id":"CRS3035RES200mN3078000E3814200","idInspire":"CRS3035RES200m<br />N3078000E3814200","commune":"AUBERS","people":"2","surfaceTotalPark":"","popParkIncluded":"n/a","popParkExcluded":"n/a","popSquareShare":"","squareMtePerCapita":"","surfaceTotalParkOms":"","popParkIncludedOms":"","popParkExcludedOms":"","popSquareShareOms":"","squareMtePerCapitaOms":"","commentParks":"","fillColor":"#060512","areaPerPeople":"","area":""}},{"type":"Feature","geometry":{"type":"Polygon","coordinates":[[[2.8264793,50.5972556],[2.8267534,50.5954675],[2.8295666,50.5956434],[2.8292926,50.5974314],[2.8264793,50.5972556]]]},"properties":{"id":"CRS3035RES200mN3078600E3814000","idInspire":"CRS3035RES200m<br />N3078600E3814000","commune":"AUBERS","people":"108","surfaceTotalPark":"","popParkIncluded":"n/a","popParkExcluded":"n/a","popSquareShare":"","squareMtePerCapita":"","surfaceTotalParkOms":"","popParkIncludedOms":"","popParkExcludedOms":"","popSquareShareOms":"","squareMtePerCapitaOms":"","commentParks":"","fillColor":"#060512","areaPerPeople":"","area":""}},{"type":"Feature","geometry":{"type":"Polygon","coordinates":[[[2.8517999,50.5988359],[2.8520731,50.5970477],[2.8548865,50.597223],[2.8546134,50.5990111],[2.8517999,50.5988359]]]},"properties":{"id":"CRS3035RES200mN3078600E3815800","idInspire":"CRS3035RES200m<br />N3078600E3815800","commune":"FROMELLES","people":"3","surfaceTotalPark":"","popParkIncluded":"n/a","popParkExcluded":"n/a","popSquareShare":"","squareMtePerCapita":"","surfaceTotalParkOms":"","popParkIncludedOms":"","popParkExcludedOms":"","popSquareShareOms":"","squareMtePerCapitaOms":"","commentParks":"","fillColor":"#060512","areaPerPeople":"","area":""}},{"type":"Feature","geometry":{"type":"Polygon","coordinates":[[[2.8689537,50.5980981],[2.8692262,50.59631],[2.8720396,50.5964848],[2.8717672,50.598273],[2.8689537,50.5980981]]]},"properties":{"id":"CRS3035RES200mN3078400E3817000","idInspire":"CRS3035RES200m<br />N3078400E3817000","commune":"FROMELLES","people":"4","surfaceTotalPark":"","popParkIncluded":"n/a","popParkExcluded":"n/a","popSquareShare":"","squareMtePerCapita":"","surfaceTotalParkOms":"","popParkIncludedOms":"","popParkExcludedOms":"","popSquareShareOms":"","squareMtePerCapitaOms":"","commentParks":"","fillColor":"#060512","areaPerPeople":"","area":""}},{"type":"Feature","geometry":{"type":"Polygon","coordinates":[[[2.8658676,50.5997114],[2.8661402,50.5979232],[2.8689537,50.5980981],[2.8686812,50.5998863],[2.8658676,50.5997114]]]},"properties":{"id":"CRS3035RES200mN3078600E3816800","idInspire":"CRS3035RES200m<br />N3078600E3816800","commune":"FROMELLES","people":"5","surfaceTotalPark":"","popParkIncluded":"n/a","popParkExcluded":"n/a","popSquareShare":"","squareMtePerCapita":"","surfaceTotalParkOms":"","popParkIncludedOms":"","popParkExcludedOms":"","popSquareShareOms":"","squareMtePerCapitaOms":"","commentParks":"","fillColor":"#060512","areaPerPeople":"","area":""}}]}